x_ray-0.3.6.dist-info/licenses/LICENSE
xray/__init__.py
xray/__main__.py
xray/custom_types.py
xray/pdf_utils.py
xray/py.typed
xray/text_utils.py
x_ray-0.3.6.dist-info/METADATA
x_ray-0.3.6.dist-info/WHEEL
x_ray-0.3.6.dist-info/entry_points.txt
x_ray-0.3.6.dist-info/top_level.txt
x_ray-0.3.6.dist-info/RECORD
