Metadata-Version: 2.4
Name: x-ray
Version: 0.3.6
Summary: A library and microservice to find bad redactions in PDFs
Author-email: Free Law Project <info@free.law>
License-Expression: BSD-2-Clause
Project-URL: Homepage, https://free.law/projects/x-ray
Project-URL: Repository, https://github.com/freelawproject/x-ray
Project-URL: Documentation, https://github.com/freelawproject/x-ray/blob/main/README.md
Project-URL: Organisation Homepage, https://free.law/
Project-URL: Change Log, https://github.com/freelawproject/x-ray/blob/main/CHANGES.md
Project-URL: Issues, https://github.com/freelawproject/x-ray/issues
Project-URL: Funding, https://www.courtlistener.com/donate/?referrer=pypi-xray
Keywords: legal,courts,redactions
Classifier: Development Status :: 5 - Production/Stable
Classifier: Intended Audience :: Developers
Classifier: Natural Language :: English
Classifier: Operating System :: OS Independent
Classifier: Programming Language :: Python
Classifier: Programming Language :: Python :: 3
Classifier: Programming Language :: Python :: 3.10
Classifier: Programming Language :: Python :: 3.11
Classifier: Programming Language :: Python :: 3.12
Classifier: Programming Language :: Python :: 3.13
Classifier: Programming Language :: Python :: 3.14
Classifier: Programming Language :: Python :: Implementation :: CPython
Classifier: Programming Language :: Python :: Implementation :: PyPy
Classifier: Topic :: Software Development :: Libraries :: Python Modules
Requires-Python: >=3.10
License-File: LICENSE
Requires-Dist: PyMuPDF==1.24.14
Requires-Dist: requests>=2.26.0
Dynamic: license-file
